<!-- ä

	Name: Advanced Questbook
	By: Crypton

-->
<Ui xmlns="http://www.runewaker.com/" xmlns:xsi="http://www.w3.org/2001/XMLSchema-instance" xsi:schemaLocation="http://www.runewaker.com/UI.xsd">
	<Button name="AdvQuestBookMapFinIcon" hidden="true" enableMouse="true" virtual="true">
		<Size>
			<AbsDimension x="24" y="24" />
		</Size>
		<Anchors>
			<Anchor point="CENTER" relativePoint="CENTER" />
		</Anchors>
		<NormalTexture file="Interface\AddOns\AdvQuestBook\images\fin.png" />
		<PushedTexture file="Interface\AddOns\AdvQuestBook\images\fin.png" />
		<HighlightTexture file="Interface\AddOns\AdvQuestBook\images\fhl.png" alphaMode="NONE" />
		<Scripts>
			<OnClick>
				AdvQuestBook_eAutoMoveToByNPCID(this:GetName());
			</OnClick>
			<OnEnter>
				AdvQuestBookIcon_OnDirection(this:GetName(), "fin", "in");
			</OnEnter>
			<OnLeave>
				AdvQuestBookIcon_OnDirection(this, nil, nil);
			</OnLeave>
		</Scripts>
	</Button>
	<Frame name="AdvQuestBookMapFinIcons" parent="WorldMapViewFrame" hidden="false" enableMouse="true" frameLevel="10000" frameStrata="HIGH">
		<Size>
			<AbsDimension x="24" y="24" />
		</Size>
		<Anchors>
			<Anchor point="CENTER" relativePoint="CENTER" />
		</Anchors>
		<Frames>
			<Button name="$parent1" inherits="AdvQuestBookMapFinIcon" />
			<Button name="$parent2" inherits="AdvQuestBookMapFinIcon" />
			<Button name="$parent3" inherits="AdvQuestBookMapFinIcon" />
			<Button name="$parent4" inherits="AdvQuestBookMapFinIcon" />
			<Button name="$parent5" inherits="AdvQuestBookMapFinIcon" />
			<Button name="$parent6" inherits="AdvQuestBookMapFinIcon" />
			<Button name="$parent7" inherits="AdvQuestBookMapFinIcon" />
			<Button name="$parent8" inherits="AdvQuestBookMapFinIcon" />
			<Button name="$parent9" inherits="AdvQuestBookMapFinIcon" />
			<Button name="$parent10" inherits="AdvQuestBookMapFinIcon" />
			<Button name="$parent11" inherits="AdvQuestBookMapFinIcon" />
			<Button name="$parent12" inherits="AdvQuestBookMapFinIcon" />
			<Button name="$parent13" inherits="AdvQuestBookMapFinIcon" />
			<Button name="$parent14" inherits="AdvQuestBookMapFinIcon" />
			<Button name="$parent15" inherits="AdvQuestBookMapFinIcon" />
			<Button name="$parent16" inherits="AdvQuestBookMapFinIcon" />
			<Button name="$parent17" inherits="AdvQuestBookMapFinIcon" />
			<Button name="$parent18" inherits="AdvQuestBookMapFinIcon" />
			<Button name="$parent19" inherits="AdvQuestBookMapFinIcon" />
			<Button name="$parent20" inherits="AdvQuestBookMapFinIcon" />
			<Button name="$parent21" inherits="AdvQuestBookMapFinIcon" />
			<Button name="$parent22" inherits="AdvQuestBookMapFinIcon" />
			<Button name="$parent23" inherits="AdvQuestBookMapFinIcon" />
			<Button name="$parent24" inherits="AdvQuestBookMapFinIcon" />
			<Button name="$parent25" inherits="AdvQuestBookMapFinIcon" />
			<Button name="$parent26" inherits="AdvQuestBookMapFinIcon" />
			<Button name="$parent27" inherits="AdvQuestBookMapFinIcon" />
			<Button name="$parent28" inherits="AdvQuestBookMapFinIcon" />
			<Button name="$parent29" inherits="AdvQuestBookMapFinIcon" />
			<Button name="$parent30" inherits="AdvQuestBookMapFinIcon" />
		</Frames>
	</Frame>
</Ui>